ivystar/__init__.py
ivystar/main.py
ivystar/src/__init__.py
ivystar/src/algorithm/__init__.py
ivystar/src/algorithm/bert_keras_predict.py
ivystar/src/algorithm/jieba_app/__init__.py
ivystar/src/algorithm/predict/__init__.py
ivystar/src/algorithm/predict/base_predict.py
ivystar/src/algorithm/predict/bert_keras_predict.py
ivystar/src/algorithm/similar/__init__.py
ivystar/src/algorithm/similar/calculate_similarity.py
ivystar/src/algorithm/spectroscopy_analysis/Envelope_spectrum.py
ivystar/src/algorithm/spectroscopy_analysis/Power_spectrum_density.py
ivystar/src/algorithm/spectroscopy_analysis/Spectrum_analysis.py
ivystar/src/algorithm/spectroscopy_analysis/__init__.py
ivystar/src/algorithm/spectroscopy_analysis/main.py
ivystar/src/algorithm/spectroscopy_analysis/smooth.py
ivystar/src/algorithm/spectroscopy_analysis/test.py
ivystar/src/algorithm/spectroscopy_analysis/test_data.py
ivystar/src/conf/__init__.py
ivystar/src/dataio/__init__.py
ivystar/src/dataio/base_helper.py
ivystar/src/dataio/csv_2_tfrecord_hilbert.py
ivystar/src/dataio/csv_2_tfrecord_iris.py
ivystar/src/dataio/hive_helper.py
ivystar/src/dataio/mongo_helper.py
ivystar/src/dataio/read_tfrecord.py
ivystar/src/dataio/tmp.py
ivystar/src/dataio/tmp2.py
ivystar/src/dataio/utils.py
ivystar/src/decorator/__init__.py
ivystar/src/decorator/test.py
ivystar/src/utils/__init__.py
ivystar/src/utils/no_use.py
ivystar/src/utils/rsa_utils.py
ivystar/src/web/__init__.py
ivystar/src/web/http_analysis.py
ivystar/src/web/http_fetch.py
ivystar/src/web/http_server.py
ivystar/src/web/tmp.py
ivystar/src/web/http_request/__init__.py
ivystar/src/web/http_request/http_analysis.py
ivystar/src/web/http_request/http_fetch.py
ivystar/src/web/http_request/http_server.py
ivystar/task/__init__.py
ivystar/task/task_url_spider.py
ivystar-0.2.12.dist-info/LICENSE.txt
ivystar-0.2.12.dist-info/METADATA
ivystar-0.2.12.dist-info/WHEEL
ivystar-0.2.12.dist-info/entry_points.txt
ivystar-0.2.12.dist-info/top_level.txt
ivystar-0.2.12.dist-info/RECORD
