Metadata-Version: 2.1
Name: ivystar
Version: 0.2.12
Summary: python tools package of ivystar
Home-page: UNKNOWN
Author: qinhaining
Author-email: qhn614@126.com
License: UNKNOWN
Keywords: command,line,tool
Platform: UNKNOWN
Requires-Dist: absl-py (==0.12.0)
Requires-Dist: aniso8601 (==8.0.0)
Requires-Dist: appdirs (==1.4.4)
Requires-Dist: apturl (==0.5.2)
Requires-Dist: argon2-cffi (==20.1.0)
Requires-Dist: astor (==0.8.1)
Requires-Dist: astunparse (==1.6.3)
Requires-Dist: async-generator (==1.10)
Requires-Dist: attrs (==19.3.0)
Requires-Dist: autocommand (==2.2.1)
Requires-Dist: Automat (==20.2.0)
Requires-Dist: backcall (==0.1.0)
Requires-Dist: bcrypt (==3.1.7)
Requires-Dist: beautifulsoup4 (==4.9.3)
Requires-Dist: bert-serving (==0.0.1)
Requires-Dist: bert-serving-client (==1.10.0)
Requires-Dist: bert-serving-server (==1.10.0)
Requires-Dist: bert4keras (==0.8.7)
Requires-Dist: bleach (==3.2.1)
Requires-Dist: blinker (==1.4)
Requires-Dist: bottle (==0.12.18)
Requires-Dist: Brlapi (==0.7.0)
Requires-Dist: bs4 (==0.0.1)
Requires-Dist: cached-property (==1.5.1)
Requires-Dist: cachetools (==4.1.1)
Requires-Dist: certifi (==2020.6.20)
Requires-Dist: cffi (==1.14.3)
Requires-Dist: chardet (==3.0.4)
Requires-Dist: chrome-gnome-shell (==0.0.0)
Requires-Dist: click (==7.1.2)
Requires-Dist: clickhouse (==0.1.7)
Requires-Dist: clickhouse-cli (==0.3.6)
Requires-Dist: clickhouse-driver (==0.1.3)
Requires-Dist: colorama (==0.4.3)
Requires-Dist: command-not-found (==0.3)
Requires-Dist: configobj (==5.0.6)
Requires-Dist: constantly (==15.1.0)
Requires-Dist: cryptography (==2.8)
Requires-Dist: cssselect (==1.1.0)
Requires-Dist: cupshelpers (==1.0)
Requires-Dist: cx-Oracle (==8.0.1)
Requires-Dist: cycler (==0.10.0)
Requires-Dist: Cython (==0.29.22)
Requires-Dist: dataclasses (==0.6)
Requires-Dist: dbus-python (==1.2.16)
Requires-Dist: decorator (==4.4.2)
Requires-Dist: defer (==1.0.6)
Requires-Dist: defusedxml (==0.6.0)
Requires-Dist: dill (==0.3.3)
Requires-Dist: distro (==1.4.0)
Requires-Dist: distro-info (==0.23ubuntu1)
Requires-Dist: dm-tree (==0.1.5)
Requires-Dist: docker (==4.1.0)
Requires-Dist: docker-compose (==1.25.0)
Requires-Dist: dockerpty (==0.4.1)
Requires-Dist: docopt (==0.6.2)
Requires-Dist: docutils (==0.16)
Requires-Dist: dominate (==2.6.0)
Requires-Dist: duplicity (==0.8.12.0)
Requires-Dist: elastic-doc-manager (==0.3.0)
Requires-Dist: elastic2-doc-manager (==1.0.0)
Requires-Dist: elasticsearch (==1.9.0)
Requires-Dist: entrypoints (==0.3)
Requires-Dist: enum34 (==1.1.10)
Requires-Dist: faiss-cpu (==1.6.5)
Requires-Dist: fake-useragent (==0.1.11)
Requires-Dist: fasteners (==0.14.1)
Requires-Dist: fasttext (==0.9.2)
Requires-Dist: fire (==0.3.1)
Requires-Dist: Flask (==1.1.2)
Requires-Dist: Flask-Bootstrap (==3.3.7.1)
Requires-Dist: Flask-Docs (==0.2.2)
Requires-Dist: Flask-RESTful (==0.3.8)
Requires-Dist: flatbuffers (==1.12)
Requires-Dist: future (==0.18.2)
Requires-Dist: gast (==0.3.3)
Requires-Dist: gevent (==20.6.2)
Requires-Dist: gin-config (==0.4.0)
Requires-Dist: google-api-core (==1.26.1)
Requires-Dist: google-api-python-client (==2.0.2)
Requires-Dist: google-auth (==1.20.1)
Requires-Dist: google-auth-httplib2 (==0.1.0)
Requires-Dist: google-auth-oauthlib (==0.4.1)
Requires-Dist: google-cloud-bigquery (==2.12.0)
Requires-Dist: google-cloud-core (==1.6.0)
Requires-Dist: google-crc32c (==1.1.2)
Requires-Dist: google-pasta (==0.2.0)
Requires-Dist: google-resumable-media (==1.2.0)
Requires-Dist: googleapis-common-protos (==1.53.0)
Requires-Dist: GPUtil (==1.4.0)
Requires-Dist: greenlet (==0.4.16)
Requires-Dist: grpcio (==1.32.0)
Requires-Dist: gunicorn (==19.9.0)
Requires-Dist: h5py (==2.10.0)
Requires-Dist: httplib2 (==0.14.0)
Requires-Dist: hyperlink (==21.0.0)
Requires-Dist: idna (==2.8)
Requires-Dist: importlib-metadata (==3.7.3)
Requires-Dist: importlib-resources (==3.2.1)
Requires-Dist: incremental (==21.3.0)
Requires-Dist: ipykernel (==5.3.4)
Requires-Dist: ipython (==7.13.0)
Requires-Dist: ipython-genutils (==0.2.0)
Requires-Dist: ipywidgets (==7.5.1)
Requires-Dist: itemadapter (==0.2.0)
Requires-Dist: itemloaders (==1.0.4)
Requires-Dist: itsdangerous (==1.1.0)
Requires-Dist: ivystar (==0.2.11)
Requires-Dist: izihawa-commons (==0.0.10)
Requires-Dist: jedi (==0.15.2)
Requires-Dist: jeepney (==0.6.0)
Requires-Dist: jieba (==0.42.1)
Requires-Dist: Jinja2 (==2.11.2)
Requires-Dist: jmespath (==0.10.0)
Requires-Dist: joblib (==0.16.0)
Requires-Dist: jsonschema (==3.2.0)
Requires-Dist: jupyter (==1.0.0)
Requires-Dist: jupyter-client (==6.1.7)
Requires-Dist: jupyter-console (==6.2.0)
Requires-Dist: jupyter-core (==4.6.3)
Requires-Dist: jupyterlab-pygments (==0.1.2)
Requires-Dist: kaggle (==1.5.12)
Requires-Dist: Keras (==2.3.1)
Requires-Dist: Keras-Applications (==1.0.8)
Requires-Dist: keras-model-specs (==1.2.0)
Requires-Dist: Keras-Preprocessing (==1.1.2)
Requires-Dist: keyring (==18.0.1)
Requires-Dist: kiwisolver (==1.2.0)
Requires-Dist: kkconst (==1.1.3)
Requires-Dist: language-selector (==0.1)
Requires-Dist: launchpadlib (==1.10.13)
Requires-Dist: lazr.restfulclient (==0.14.2)
Requires-Dist: lazr.uri (==1.0.3)
Requires-Dist: lockfile (==0.12.2)
Requires-Dist: louis (==3.12.0)
Requires-Dist: lxml (==4.5.2)
Requires-Dist: macaroonbakery (==1.3.1)
Requires-Dist: Mako (==1.1.0)
Requires-Dist: Markdown (==3.2.2)
Requires-Dist: markup (==0.2)
Requires-Dist: MarkupSafe (==1.1.0)
Requires-Dist: matplotlib (==3.3.1)
Requires-Dist: mistune (==0.8.4)
Requires-Dist: mock (==4.0.3)
Requires-Dist: mongo-connector (==3.1.1)
Requires-Dist: monotonic (==1.5)
Requires-Dist: more-itertools (==4.2.0)
Requires-Dist: msgpack (==0.6.2)
Requires-Dist: multidict (==5.1.0)
Requires-Dist: nbclient (==0.5.0)
Requires-Dist: nbconvert (==6.0.7)
Requires-Dist: nbformat (==5.0.7)
Requires-Dist: nest-asyncio (==1.4.1)
Requires-Dist: netifaces (==0.10.4)
Requires-Dist: networkx (==1.10)
Requires-Dist: notebook (==6.1.4)
Requires-Dist: numpy (==1.19.5)
Requires-Dist: oauth2client (==4.1.3)
Requires-Dist: oauthlib (==3.1.0)
Requires-Dist: object-detection (==0.1)
Requires-Dist: olefile (==0.46)
Requires-Dist: opencv-python-headless (==4.5.1.48)
Requires-Dist: opt-einsum (==3.3.0)
Requires-Dist: packaging (==20.4)
Requires-Dist: pandas (==1.1.1)
Requires-Dist: pandocfilters (==1.4.2)
Requires-Dist: paramiko (==2.6.0)
Requires-Dist: parse (==1.19.0)
Requires-Dist: parsel (==1.6.0)
Requires-Dist: parso (==0.5.2)
Requires-Dist: pbr (==5.5.1)
Requires-Dist: pexpect (==4.6.0)
Requires-Dist: pickleshare (==0.7.5)
Requires-Dist: Pillow (==7.0.0)
Requires-Dist: pip (==20.0.2)
Requires-Dist: pkginfo (==1.7.0)
Requires-Dist: prometheus-client (==0.8.0)
Requires-Dist: promise (==2.3)
Requires-Dist: prompt-toolkit (==2.0.10)
Requires-Dist: Protego (==0.1.16)
Requires-Dist: proto-plus (==1.18.1)
Requires-Dist: protobuf (==3.13.0)
Requires-Dist: psutil (==5.5.1)
Requires-Dist: ptyprocess (==0.6.0)
Requires-Dist: py-cpuinfo (==7.0.0)
Requires-Dist: pyasn1 (==0.4.8)
Requires-Dist: pyasn1-modules (==0.2.8)
Requires-Dist: pybind11 (==2.5.0)
Requires-Dist: pycairo (==1.16.2)
Requires-Dist: pycocotools (==2.0.2)
Requires-Dist: pycparser (==2.20)
Requires-Dist: pycups (==1.9.73)
Requires-Dist: PyDispatcher (==2.0.5)
Requires-Dist: pyee (==8.1.0)
Requires-Dist: pyflakes (==2.2.0)
Requires-Dist: pyfpgrowth (==1.0)
Requires-Dist: Pygments (==2.7.2)
Requires-Dist: PyGObject (==3.36.0)
Requires-Dist: PyHive (==0.6.3)
Requires-Dist: PyJWT (==1.7.1)
Requires-Dist: pymacaroons (==0.13.0)
Requires-Dist: pymongo (==3.11.0)
Requires-Dist: PyMySQL (==0.10.0)
Requires-Dist: PyNaCl (==1.3.0)
Requires-Dist: pynvim (==0.4.1)
Requires-Dist: pyOpenSSL (==20.0.1)
Requires-Dist: pyparsing (==2.4.7)
Requires-Dist: pyppeteer (==0.2.5)
Requires-Dist: PyQt5 (==5.14.1)
Requires-Dist: pyquery (==1.4.3)
Requires-Dist: pyRFC3339 (==1.1)
Requires-Dist: pyrsistent (==0.15.5)
Requires-Dist: python-apt (==2.0.0+ubuntu0.20.4.3)
Requires-Dist: python-dateutil (==2.7.3)
Requires-Dist: python-debian (==0.1.36ubuntu1)
Requires-Dist: python-docx (==0.8.10)
Requires-Dist: python-slugify (==4.0.1)
Requires-Dist: pytz (==2019.3)
Requires-Dist: pyxattr (==0.6.1)
Requires-Dist: pyxdg (==0.26)
Requires-Dist: PyYAML (==5.3.1)
Requires-Dist: pyzmq (==19.0.2)
Requires-Dist: qtconsole (==4.7.7)
Requires-Dist: QtPy (==1.9.0)
Requires-Dist: queuelib (==1.5.0)
Requires-Dist: readme-renderer (==29.0)
Requires-Dist: redis (==3.5.3)
Requires-Dist: reportlab (==3.5.34)
Requires-Dist: requests (==2.22.0)
Requires-Dist: requests-html (==0.10.0)
Requires-Dist: requests-oauthlib (==1.3.0)
Requires-Dist: requests-toolbelt (==0.9.1)
Requires-Dist: requests-unixsocket (==0.2.0)
Requires-Dist: rfc3986 (==1.4.0)
Requires-Dist: rsa (==4.6)
Requires-Dist: schedule (==0.6.0)
Requires-Dist: scikit-learn (==0.23.2)
Requires-Dist: scipy (==1.4.1)
Requires-Dist: Scrapy (==2.4.1)
Requires-Dist: SecretStorage (==2.3.1)
Requires-Dist: selenium (==3.141.0)
Requires-Dist: Send2Trash (==1.5.0)
Requires-Dist: sentencepiece (==0.1.95)
Requires-Dist: seqeval (==1.2.2)
Requires-Dist: service-identity (==18.1.0)
Requires-Dist: setuptools (==50.3.2)
Requires-Dist: simplejson (==3.16.0)
Requires-Dist: sip (==4.19.21)
Requires-Dist: six (==1.15.0)
Requires-Dist: sklearn (==0.0)
Requires-Dist: soupsieve (==2.1)
Requires-Dist: sqlparse (==0.4.1)
Requires-Dist: ssh-import-id (==5.10)
Requires-Dist: systemd-python (==234)
Requires-Dist: tensorboard (==2.4.1)
Requires-Dist: tensorboard-plugin-wit (==1.7.0)
Requires-Dist: tensorflow (==2.4.1)
Requires-Dist: tensorflow-addons (==0.12.1)
Requires-Dist: tensorflow-datasets (==4.2.0)
Requires-Dist: tensorflow-estimator (==2.4.0)
Requires-Dist: tensorflow-hub (==0.11.0)
Requires-Dist: tensorflow-metadata (==0.28.0)
Requires-Dist: tensorflow-model-optimization (==0.5.0)
Requires-Dist: tensorflow-serving-client (==1.0.0)
Requires-Dist: termcolor (==1.1.0)
Requires-Dist: terminado (==0.9.1)
Requires-Dist: testpath (==0.4.4)
Requires-Dist: testresources (==2.0.1)
Requires-Dist: text-unidecode (==1.3)
Requires-Dist: texttable (==1.6.2)
Requires-Dist: tf-models-official (==2.4.0)
Requires-Dist: tf-slim (==1.1.0)
Requires-Dist: threadpoolctl (==2.1.0)
Requires-Dist: thrift (==0.13.0)
Requires-Dist: tornado (==6.0.4)
Requires-Dist: tqdm (==4.51.0)
Requires-Dist: traitlets (==4.3.3)
Requires-Dist: treelib (==1.6.1)
Requires-Dist: twine (==3.4.1)
Requires-Dist: Twisted (==21.2.0)
Requires-Dist: typeguard (==2.11.1)
Requires-Dist: typing-extensions (==3.7.4.3)
Requires-Dist: tzlocal (==2.1)
Requires-Dist: ubuntu-advantage-tools (==20.3)
Requires-Dist: ubuntu-drivers-common (==0.0.0)
Requires-Dist: ufw (==0.36)
Requires-Dist: unattended-upgrades (==0.1)
Requires-Dist: uritemplate (==3.0.1)
Requires-Dist: urllib3 (==1.25.8)
Requires-Dist: usb-creator (==0.3.7)
Requires-Dist: visitor (==0.1.3)
Requires-Dist: w3lib (==1.22.0)
Requires-Dist: wadllib (==1.3.3)
Requires-Dist: wcwidth (==0.1.8)
Requires-Dist: webencodings (==0.5.1)
Requires-Dist: websocket-client (==0.53.0)
Requires-Dist: websockets (==8.1)
Requires-Dist: Werkzeug (==1.0.1)
Requires-Dist: wheel (==0.35.1)
Requires-Dist: Whoosh (==2.7.4)
Requires-Dist: widgetsnbextension (==3.5.1)
Requires-Dist: wrapt (==1.12.1)
Requires-Dist: xgboost (==1.2.1)
Requires-Dist: xkit (==0.0.0)
Requires-Dist: xlrd (==1.2.0)
Requires-Dist: xlwt (==1.3.0)
Requires-Dist: youtube-dl (==2020.3.24)
Requires-Dist: zipp (==1.0.0)
Requires-Dist: zmq (==0.0.0)
Requires-Dist: zope.event (==4.4)
Requires-Dist: zope.interface (==5.1.0)
